bonobo_factories/__init__.py
bonobo_factories/_version.py
bonobo_factories/factory.py
bonobo_factories-0.1.0.dist-info/DESCRIPTION.rst
bonobo_factories-0.1.0.dist-info/METADATA
bonobo_factories-0.1.0.dist-info/RECORD
bonobo_factories-0.1.0.dist-info/WHEEL
bonobo_factories-0.1.0.dist-info/metadata.json
bonobo_factories-0.1.0.dist-info/top_level.txt
