Metadata-Version: 2.0
Name: bonobo-factories
Version: 0.1.0
Summary: Bonobo Factories
Home-page: UNKNOWN
Author: Romain Dorgueil
Author-email: romain@dorgueil.net
License: Apache License, Version 2.0
Platform: UNKNOWN
Requires-Dist: bonobo (>=0.5.1)
Provides-Extra: dev
Requires-Dist: bonobo (>=0.5.1); extra == 'dev'
Requires-Dist: coverage (<5.0,>=4.4); extra == 'dev'
Requires-Dist: pytest (<4.0,>=3.1); extra == 'dev'
Requires-Dist: pytest-cov (<3.0,>=2.5); extra == 'dev'
